tagordo/__init__.py
tagordo/main.py
tagordo-0.1.0.dist-info/entry_points.txt
tagordo-0.1.0.dist-info/METADATA
tagordo-0.1.0.dist-info/WHEEL
tagordo-0.1.0.dist-info/RECORD
