Metadata-Version: 2.1
Name: tagordo
Version: 0.1.0
Summary: Tiny python script to check if given checkpoints are up-to-date with a given cron schedule
Home-page: https://github.com/mathiazom/tagordo
Author: Mathias O. Myklebust
Author-email: mathias@oterbust.no
Requires-Python: >=3.10,<4.0
Classifier: Development Status :: 4 - Beta
Classifier: Intended Audience :: Developers
Classifier: License :: OSI Approved :: MIT License
Classifier: Operating System :: OS Independent
Classifier: Programming Language :: Python :: 3
Classifier: Programming Language :: Python :: 3.10
Classifier: Programming Language :: Python :: 3.11
Classifier: Programming Language :: Python :: 3.10
Requires-Dist: croniter (>=1.3.8,<2.0.0)
Requires-Dist: typer[all] (>=0.3.0,<0.4.0)
Project-URL: Bug Tracker, https://github.com/mathiazom/tagordo/issues
Project-URL: Repository, https://github.com/mathiazom/tagordo
